{
  "id": "http://opencurricula/berlin-brandenburg/themes/8fcfa231-f1dd-4b09-baef-bf4f2ed5fa62",
  "type": "Concept",
  "followers": "https://test.skohub.io/followers?subject=opencurricula%2Fberlin-brandenburg%2Fthemes%2F8fcfa231-f1dd-4b09-baef-bf4f2ed5fa62",
  "inbox": "https://test.skohub.io/inbox?target=opencurricula%2Fberlin-brandenburg%2Fthemes%2F8fcfa231-f1dd-4b09-baef-bf4f2ed5fa62",
  "prefLabel": {
    "de": "Die Grenzen des Sichtbaren – optische Geräte"
  },
  "note": {
    "de": [
      "C-NW-3-2"
    ]
  },
  "narrower": [
    {
      "id": "http://opencurricula/berlin-brandenburg/themes/1db5418f-742c-4600-bb44-eb5f232d34d4",
      "prefLabel": {
        "de": "Die Vielfalt der Augen im Tierreich"
      },
      "note": {
        "de": [
          "C-NW-3-2-1-8"
        ]
      }
    },
    {
      "id": "http://opencurricula/berlin-brandenburg/themes/29cae84c-8b23-4bd0-8517-ef13373ae785",
      "prefLabel": {
        "de": "Das menschliche Auge"
      },
      "note": {
        "de": [
          "C-NW-3-2-1-5"
        ]
      }
    },
    {
      "id": "http://opencurricula/berlin-brandenburg/themes/45701504-9cd5-4cdd-b743-57da8181b23d",
      "prefLabel": {
        "de": "Blick in den Mikrokosmos – Mikroskope"
      },
      "note": {
        "de": [
          "C-NW-3-2-1-2"
        ]
      }
    },
    {
      "id": "http://opencurricula/berlin-brandenburg/themes/6f3dbd8d-8db4-4df0-8f3d-c2389cfe2593",
      "prefLabel": {
        "de": "Sehhilfen"
      },
      "note": {
        "de": [
          "C-NW-3-2-1-9"
        ]
      }
    },
    {
      "id": "http://opencurricula/berlin-brandenburg/themes/bfc35789-2535-4358-b58b-d4170eaee92a",
      "prefLabel": {
        "de": "Linsen brechen Licht"
      },
      "note": {
        "de": [
          "C-NW-3-2-1-1"
        ]
      }
    },
    {
      "id": "http://opencurricula/berlin-brandenburg/themes/ee966077-e9d2-4b71-b0be-fd1347f29cd3",
      "prefLabel": {
        "de": "Fotoapparat"
      },
      "note": {
        "de": [
          "C-NW-3-2-1-7"
        ]
      }
    },
    {
      "id": "http://opencurricula/berlin-brandenburg/themes/f3b02969-5f51-4476-adfe-0208dd3d8122",
      "prefLabel": {
        "de": "Prismen im Lichtweg"
      },
      "note": {
        "de": [
          "C-NW-3-2-1-4"
        ]
      }
    },
    {
      "id": "http://opencurricula/berlin-brandenburg/themes/f43eea33-e3ef-4edf-bcab-3db690e817b4",
      "prefLabel": {
        "de": "Glas"
      },
      "note": {
        "de": [
          "C-NW-3-2-1-3"
        ]
      }
    },
    {
      "id": "http://opencurricula/berlin-brandenburg/themes/fc4cb86f-8841-4ab7-9d71-da1f4e304138",
      "prefLabel": {
        "de": "Blick ins Unendliche – Fernrohre"
      },
      "note": {
        "de": [
          "C-NW-3-2-1-6"
        ]
      }
    }
  ],
  "broader": {
    "id": "http://opencurricula/berlin-brandenburg/themes/266cc843-07ef-46df-92e6-e29ddfbedd8c",
    "prefLabel": {
      "de": "Naturwissenschaften 7 – 10"
    }
  },
  "inScheme": {
    "id": "http://opencurricula/berlin-brandenburg/themes/",
    "title": {
      "de": "RLP Berlin-Brandenburg Themen"
    }
  },
  "@context": {
    "@version": 1.1,
    "id": "@id",
    "type": "@type",
    "@vocab": "http://www.w3.org/2004/02/skos/core#",
    "xsd": "http://www.w3.org/2001/XMLSchema#",
    "dct": "http://purl.org/dc/terms/",
    "schema": "http://schema.org/",
    "vann": "http://purl.org/vocab/vann/",
    "as": "https://www.w3.org/ns/activitystreams#",
    "ldp": "http://www.w3.org/ns/ldp#",
    "title": {
      "@id": "dct:title",
      "@container": "@language"
    },
    "description": {
      "@id": "dct:description",
      "@container": "@language"
    },
    "issued": {
      "@id": "dct:issued",
      "@type": "xsd:date"
    },
    "created": {
      "@id": "dct:created",
      "@type": "xsd:date"
    },
    "modified": {
      "@id": "dct:modified",
      "@type": "xsd:date"
    },
    "creator": "dct:creator",
    "publisher": "dct:publisher",
    "preferredNamespacePrefix": "vann:preferredNamespacePrefix",
    "preferredNamespaceUri": "vann:preferredNamespaceUri",
    "isBasedOn": "schema:isBasedOn",
    "source": "dct:source",
    "prefLabel": {
      "@container": "@language"
    },
    "hiddenLabel": {
      "@container": [
        "@language",
        "@set"
      ]
    },
    "altLabel": {
      "@container": [
        "@language",
        "@set"
      ]
    },
    "definition": {
      "@container": "@language"
    },
    "scopeNote": {
      "@container": [
        "@language",
        "@set"
      ]
    },
    "note": {
      "@container": [
        "@language",
        "@set"
      ]
    },
    "notation": {
      "@container": "@set"
    },
    "narrower": {
      "@container": "@set"
    },
    "narrowerTransitive": {
      "@container": "@set"
    },
    "broaderTransitive": {
      "@container": "@set"
    },
    "followers": "as:followers",
    "inbox": "ldp:inbox"
  }
}