{
  "id": "http://w3id.org/openeduhub/vocabs/curriculum_bb/f9337e06-25ce-4fa3-9e63-87319da06cfa",
  "type": "Concept",
  "followers": "https://test.skohub.io/followers?subject=w3id.org%2Fopeneduhub%2Fvocabs%2Fcurriculum_bb%2Ff9337e06-25ce-4fa3-9e63-87319da06cfa",
  "inbox": "https://test.skohub.io/inbox?target=w3id.org%2Fopeneduhub%2Fvocabs%2Fcurriculum_bb%2Ff9337e06-25ce-4fa3-9e63-87319da06cfa",
  "prefLabel": {
    "de": "ihren Schreibprozess unter Zuhilfenahme verschiedener Techniken und Hilfsmittel zunehmend selbstständig steuern"
  },
  "broader": {
    "id": "http://w3id.org/openeduhub/vocabs/curriculum_bb/5536f86e-ae75-41ea-a4b1-2854a5e26ef9",
    "prefLabel": {
      "de": "G"
    }
  },
  "inScheme": {
    "id": "http://w3id.org/openeduhub/vocabs/curriculum_bb/",
    "title": {
      "de": "curriculum_bb"
    }
  },
  "@context": {
    "@version": 1.1,
    "id": "@id",
    "type": "@type",
    "@vocab": "http://www.w3.org/2004/02/skos/core#",
    "xsd": "http://www.w3.org/2001/XMLSchema#",
    "dct": "http://purl.org/dc/terms/",
    "schema": "http://schema.org/",
    "vann": "http://purl.org/vocab/vann/",
    "title": {
      "@id": "dct:title",
      "@container": "@language"
    },
    "description": {
      "@id": "dct:description",
      "@container": "@language"
    },
    "issued": {
      "@id": "dct:issued",
      "@type": "xsd:date"
    },
    "created": {
      "@id": "dct:created",
      "@type": "xsd:date"
    },
    "modified": {
      "@id": "dct:modified",
      "@type": "xsd:date"
    },
    "creator": "dct:creator",
    "publisher": "dct:publisher",
    "preferredNamespacePrefix": "vann:preferredNamespacePrefix",
    "preferredNamespaceUri": "vann:preferredNamespaceUri",
    "isBasedOn": "schema:isBasedOn",
    "source": "dct:source",
    "prefLabel": {
      "@container": "@language"
    },
    "hiddenLabel": {
      "@container": [
        "@language",
        "@set"
      ]
    },
    "altLabel": {
      "@container": [
        "@language",
        "@set"
      ]
    },
    "definition": {
      "@container": "@language"
    },
    "scopeNote": {
      "@container": "@language"
    },
    "note": {
      "@container": "@language"
    },
    "notation": {
      "@container": "@set"
    },
    "narrower": {
      "@container": "@set"
    },
    "narrowerTransitive": {
      "@container": "@set"
    },
    "broaderTransitive": {
      "@container": "@set"
    }
  }
}