{
  "id": "http://opencurricula/berlin-brandenburg/408780ef-26d8-4941-a318-521147537274",
  "type": "Concept",
  "followers": "https://test.skohub.io/followers?subject=opencurricula%2Fberlin-brandenburg%2F408780ef-26d8-4941-a318-521147537274",
  "inbox": "https://test.skohub.io/inbox?target=opencurricula%2Fberlin-brandenburg%2F408780ef-26d8-4941-a318-521147537274",
  "prefLabel": {
    "de": "FGH"
  },
  "narrower": [
    {
      "id": "http://opencurricula/berlin-brandenburg/831c4e24-ed6a-406c-8e60-81c59f8471ee",
      "prefLabel": {
        "de": "aus weiteren geografischen Medien wie Tabellen, Diagrammen, Karikaturen, Satelliten- und Luftaufnahmen, Modellen sowie audiovisuellen Medien raumspezifische Funktionen, Strukturen oder Prozesse ermitteln"
      }
    }
  ],
  "broader": {
    "id": "http://opencurricula/berlin-brandenburg/b20abeeb-a412-4347-b581-5184673eeaa2",
    "prefLabel": {
      "de": "Informationen  gewinnen"
    }
  },
  "inScheme": {
    "id": "http://opencurricula/berlin-brandenburg/",
    "title": {
      "de": "curriculum_bb"
    }
  },
  "@context": {
    "@version": 1.1,
    "id": "@id",
    "type": "@type",
    "@vocab": "http://www.w3.org/2004/02/skos/core#",
    "xsd": "http://www.w3.org/2001/XMLSchema#",
    "dct": "http://purl.org/dc/terms/",
    "schema": "http://schema.org/",
    "vann": "http://purl.org/vocab/vann/",
    "title": {
      "@id": "dct:title",
      "@container": "@language"
    },
    "description": {
      "@id": "dct:description",
      "@container": "@language"
    },
    "issued": {
      "@id": "dct:issued",
      "@type": "xsd:date"
    },
    "created": {
      "@id": "dct:created",
      "@type": "xsd:date"
    },
    "modified": {
      "@id": "dct:modified",
      "@type": "xsd:date"
    },
    "creator": "dct:creator",
    "publisher": "dct:publisher",
    "preferredNamespacePrefix": "vann:preferredNamespacePrefix",
    "preferredNamespaceUri": "vann:preferredNamespaceUri",
    "isBasedOn": "schema:isBasedOn",
    "source": "dct:source",
    "prefLabel": {
      "@container": "@language"
    },
    "hiddenLabel": {
      "@container": [
        "@language",
        "@set"
      ]
    },
    "altLabel": {
      "@container": [
        "@language",
        "@set"
      ]
    },
    "definition": {
      "@container": "@language"
    },
    "scopeNote": {
      "@container": "@language"
    },
    "note": {
      "@container": "@language"
    },
    "notation": {
      "@container": "@set"
    },
    "narrower": {
      "@container": "@set"
    },
    "narrowerTransitive": {
      "@container": "@set"
    },
    "broaderTransitive": {
      "@container": "@set"
    }
  }
}