{
  "id": "http://opencurricula/berlin-brandenburg/905fc6b8-4e52-4656-bdb0-072bcc65ce3b",
  "type": "Concept",
  "followers": "https://test.skohub.io/followers?subject=opencurricula%2Fberlin-brandenburg%2F905fc6b8-4e52-4656-bdb0-072bcc65ce3b",
  "inbox": "https://test.skohub.io/inbox?target=opencurricula%2Fberlin-brandenburg%2F905fc6b8-4e52-4656-bdb0-072bcc65ce3b",
  "prefLabel": {
    "de": "G"
  },
  "narrower": [
    {
      "id": "http://opencurricula/berlin-brandenburg/43f12855-8d44-4ff2-b7ac-f412b591a6b3",
      "prefLabel": {
        "de": "einen Kommentar oder eine Stellungnahme unter Nutzung geeigneter Textmuster und -bausteine verfassen"
      }
    },
    {
      "id": "http://opencurricula/berlin-brandenburg/a0a258cc-45c1-43a1-ab43-420dd3e8d04e",
      "prefLabel": {
        "de": "weitere sprachliche Mittel (z. B. Passiv/ Aktiv, indirekte Rede) nutzen"
      }
    },
    {
      "id": "http://opencurricula/berlin-brandenburg/e2a7d5d4-728e-4be3-85b8-919162e45f7c",
      "prefLabel": {
        "de": "Zusammenfassungen, Protokolle unter Nutzung geeigneter Textmuster und -bausteine (z. B. Kraft einwirken, ausüben) schreiben"
      }
    },
    {
      "id": "http://opencurricula/berlin-brandenburg/f00225db-5e0e-4538-9be6-b22e4a0653e4",
      "prefLabel": {
        "de": "Textmuster (z. B. formeller Brief, Bauanleitung, Tabelle) und fachspezifische Textbausteine (z. B. Formelschreibweise) anwenden"
      }
    }
  ],
  "broader": {
    "id": "http://opencurricula/berlin-brandenburg/ea7588fd-3e3a-465d-98fe-0710014c720d",
    "prefLabel": {
      "de": "Texte schreiben"
    }
  },
  "inScheme": {
    "id": "http://opencurricula/berlin-brandenburg/",
    "title": {
      "de": "curriculum_bb"
    }
  },
  "@context": {
    "@version": 1.1,
    "id": "@id",
    "type": "@type",
    "@vocab": "http://www.w3.org/2004/02/skos/core#",
    "xsd": "http://www.w3.org/2001/XMLSchema#",
    "dct": "http://purl.org/dc/terms/",
    "schema": "http://schema.org/",
    "vann": "http://purl.org/vocab/vann/",
    "title": {
      "@id": "dct:title",
      "@container": "@language"
    },
    "description": {
      "@id": "dct:description",
      "@container": "@language"
    },
    "issued": {
      "@id": "dct:issued",
      "@type": "xsd:date"
    },
    "created": {
      "@id": "dct:created",
      "@type": "xsd:date"
    },
    "modified": {
      "@id": "dct:modified",
      "@type": "xsd:date"
    },
    "creator": "dct:creator",
    "publisher": "dct:publisher",
    "preferredNamespacePrefix": "vann:preferredNamespacePrefix",
    "preferredNamespaceUri": "vann:preferredNamespaceUri",
    "isBasedOn": "schema:isBasedOn",
    "source": "dct:source",
    "prefLabel": {
      "@container": "@language"
    },
    "hiddenLabel": {
      "@container": [
        "@language",
        "@set"
      ]
    },
    "altLabel": {
      "@container": [
        "@language",
        "@set"
      ]
    },
    "definition": {
      "@container": "@language"
    },
    "scopeNote": {
      "@container": "@language"
    },
    "note": {
      "@container": "@language"
    },
    "notation": {
      "@container": "@set"
    },
    "narrower": {
      "@container": "@set"
    },
    "narrowerTransitive": {
      "@container": "@set"
    },
    "broaderTransitive": {
      "@container": "@set"
    }
  }
}