{
  "id": "http://opencurricula/berlin-brandenburg/a94a04e7-f274-406f-950f-adfc85f8acde",
  "type": "Concept",
  "followers": "https://test.skohub.io/followers?subject=opencurricula%2Fberlin-brandenburg%2Fa94a04e7-f274-406f-950f-adfc85f8acde",
  "inbox": "https://test.skohub.io/inbox?target=opencurricula%2Fberlin-brandenburg%2Fa94a04e7-f274-406f-950f-adfc85f8acde",
  "prefLabel": {
    "de": "Mit naturwissenschaftlichen Größen umgehen"
  },
  "note": {
    "de": [
      "C-AS-K2-4-1"
    ]
  },
  "narrower": [
    {
      "id": "http://opencurricula/berlin-brandenburg/342bb93c-264c-4464-aaf7-ca9818dee90a",
      "prefLabel": {
        "de": "E"
      },
      "note": {
        "de": [
          "C-AS-K2-4-1-E"
        ]
      }
    },
    {
      "id": "http://opencurricula/berlin-brandenburg/43edaa9e-1790-45e7-828d-88be5a176270",
      "prefLabel": {
        "de": "H"
      },
      "note": {
        "de": [
          "C-AS-K2-4-1-H"
        ]
      }
    },
    {
      "id": "http://opencurricula/berlin-brandenburg/9545dff5-ff30-4055-ad0c-a330a9cff2f3",
      "prefLabel": {
        "de": "G"
      },
      "note": {
        "de": [
          "C-AS-K2-4-1-G"
        ]
      }
    },
    {
      "id": "http://opencurricula/berlin-brandenburg/f53dacca-47cc-45a9-bcce-24100146b503",
      "prefLabel": {
        "de": "F"
      },
      "note": {
        "de": [
          "C-AS-K2-4-1-F"
        ]
      }
    }
  ],
  "broader": {
    "id": "http://opencurricula/berlin-brandenburg/dd1fe9ba-3ab9-43d1-94af-f94bc178a80b",
    "prefLabel": {
      "de": "Elemente der Mathematik anwenden"
    }
  },
  "inScheme": {
    "id": "http://opencurricula/berlin-brandenburg/"
  },
  "@context": {
    "@version": 1.1,
    "id": "@id",
    "type": "@type",
    "@vocab": "http://www.w3.org/2004/02/skos/core#",
    "xsd": "http://www.w3.org/2001/XMLSchema#",
    "dct": "http://purl.org/dc/terms/",
    "schema": "http://schema.org/",
    "vann": "http://purl.org/vocab/vann/",
    "as": "https://www.w3.org/ns/activitystreams#",
    "ldp": "http://www.w3.org/ns/ldp#",
    "title": {
      "@id": "dct:title",
      "@container": "@language"
    },
    "description": {
      "@id": "dct:description",
      "@container": "@language"
    },
    "issued": {
      "@id": "dct:issued",
      "@type": "xsd:date"
    },
    "created": {
      "@id": "dct:created",
      "@type": "xsd:date"
    },
    "modified": {
      "@id": "dct:modified",
      "@type": "xsd:date"
    },
    "creator": "dct:creator",
    "publisher": "dct:publisher",
    "preferredNamespacePrefix": "vann:preferredNamespacePrefix",
    "preferredNamespaceUri": "vann:preferredNamespaceUri",
    "isBasedOn": "schema:isBasedOn",
    "source": "dct:source",
    "prefLabel": {
      "@container": "@language"
    },
    "hiddenLabel": {
      "@container": [
        "@language",
        "@set"
      ]
    },
    "altLabel": {
      "@container": [
        "@language",
        "@set"
      ]
    },
    "definition": {
      "@container": "@language"
    },
    "scopeNote": {
      "@container": [
        "@language",
        "@set"
      ]
    },
    "note": {
      "@container": [
        "@language",
        "@set"
      ]
    },
    "notation": {
      "@container": "@set"
    },
    "narrower": {
      "@container": "@set"
    },
    "narrowerTransitive": {
      "@container": "@set"
    },
    "broaderTransitive": {
      "@container": "@set"
    },
    "followers": "as:followers",
    "inbox": "ldp:inbox"
  }
}