{
  "id": "http://opencurricula/berlin-brandenburg/e9e54d69-d7e0-4e88-9b2d-177f7c79c971",
  "type": "Concept",
  "followers": "https://test.skohub.io/followers?subject=opencurricula%2Fberlin-brandenburg%2Fe9e54d69-d7e0-4e88-9b2d-177f7c79c971",
  "inbox": "https://test.skohub.io/inbox?target=opencurricula%2Fberlin-brandenburg%2Fe9e54d69-d7e0-4e88-9b2d-177f7c79c971",
  "prefLabel": {
    "de": "Sprachlernkompetenz"
  },
  "narrower": [
    {
      "id": "http://opencurricula/berlin-brandenburg/3ca508b2-8b57-4e1a-8fe2-317a76d0e469",
      "prefLabel": {
        "de": "EFGH"
      }
    },
    {
      "id": "http://opencurricula/berlin-brandenburg/4978908e-7b6f-44d7-9814-ec3d73d14c17",
      "prefLabel": {
        "de": "AB"
      }
    },
    {
      "id": "http://opencurricula/berlin-brandenburg/d24b7de5-b12a-4daa-b05d-d07521e4916c",
      "prefLabel": {
        "de": "CD"
      }
    }
  ],
  "broader": {
    "id": "http://opencurricula/berlin-brandenburg/07fbcc7c-92d3-4ded-b1fb-ffa335a59887",
    "prefLabel": {
      "de": "Sprachlernkompetenz"
    }
  },
  "inScheme": {
    "id": "http://opencurricula/berlin-brandenburg/",
    "title": {
      "de": "curriculum_bb"
    }
  },
  "@context": {
    "@version": 1.1,
    "id": "@id",
    "type": "@type",
    "@vocab": "http://www.w3.org/2004/02/skos/core#",
    "xsd": "http://www.w3.org/2001/XMLSchema#",
    "dct": "http://purl.org/dc/terms/",
    "schema": "http://schema.org/",
    "vann": "http://purl.org/vocab/vann/",
    "as": "https://www.w3.org/ns/activitystreams#",
    "ldp": "http://www.w3.org/ns/ldp#",
    "title": {
      "@id": "dct:title",
      "@container": "@language"
    },
    "description": {
      "@id": "dct:description",
      "@container": "@language"
    },
    "issued": {
      "@id": "dct:issued",
      "@type": "xsd:date"
    },
    "created": {
      "@id": "dct:created",
      "@type": "xsd:date"
    },
    "modified": {
      "@id": "dct:modified",
      "@type": "xsd:date"
    },
    "creator": "dct:creator",
    "publisher": "dct:publisher",
    "preferredNamespacePrefix": "vann:preferredNamespacePrefix",
    "preferredNamespaceUri": "vann:preferredNamespaceUri",
    "isBasedOn": "schema:isBasedOn",
    "source": "dct:source",
    "prefLabel": {
      "@container": "@language"
    },
    "hiddenLabel": {
      "@container": [
        "@language",
        "@set"
      ]
    },
    "altLabel": {
      "@container": [
        "@language",
        "@set"
      ]
    },
    "definition": {
      "@container": "@language"
    },
    "scopeNote": {
      "@container": [
        "@language",
        "@set"
      ]
    },
    "note": {
      "@container": [
        "@language",
        "@set"
      ]
    },
    "notation": {
      "@container": "@set"
    },
    "narrower": {
      "@container": "@set"
    },
    "narrowerTransitive": {
      "@container": "@set"
    },
    "broaderTransitive": {
      "@container": "@set"
    },
    "followers": "as:followers",
    "inbox": "ldp:inbox"
  }
}